Metadata-Version: 1.2
Name: awsdumplogs
Version: 0.1.1
Summary: aws logs dump and analytics tool
Home-page: https://github.com/xinhuagu/dumplogs
Author: Xinhua Gu
Author-email: xinhua.gu@gmail.com
License: LICENSE.txt
Platform: any
Requires-Python: >=3.5.*
